foam2dolfinx/__init__.py
foam2dolfinx/_version.py
foam2dolfinx/open_foam_reader.py
foam2dolfinx-1.0.dist-info/licenses/LICENSE
foam2dolfinx-1.0.dist-info/METADATA
foam2dolfinx-1.0.dist-info/WHEEL
foam2dolfinx-1.0.dist-info/top_level.txt
foam2dolfinx-1.0.dist-info/RECORD
