Metadata-Version: 2.4
Name: foam2dolfinx
Version: 1.0
Summary: Convert OpenFOAM files to dolfinx functions
Author-email: Remi Delaporte-Mathurin <rdelaportemathurin@gmail.com>, James Dark <darkj385@mit.edu>
License: MIT License
Project-URL: Homepage, https://github.com/festim-dev/foam2dolfinx
Project-URL: Issues, https://github.com/festim-dev/foam2dolfinx/issues
Classifier: Natural Language :: English
Classifier: Topic :: Scientific/Engineering
Classifier: Programming Language :: Python :: 3.9
Classifier: Programming Language :: Python :: 3.10
Classifier: Programming Language :: Python :: 3.11
Classifier: Programming Language :: Python :: 3.12
Classifier: Programming Language :: Python :: 3.13
Classifier: License :: OSI Approved :: Apache Software License
Classifier: Operating System :: OS Independent
Requires-Python: >=3.9
License-File: LICENSE
Requires-Dist: fenics-dolfinx>=0.9.0
Requires-Dist: pyvista
Provides-Extra: test
Requires-Dist: pytest>=5.4.3; extra == "test"
Requires-Dist: pytest-cov; extra == "test"
Provides-Extra: lint
Requires-Dist: ruff; extra == "lint"
Requires-Dist: mypy; extra == "lint"
Provides-Extra: docs
Requires-Dist: sphinx; extra == "docs"
Requires-Dist: sphinx-book-theme; extra == "docs"
Requires-Dist: sphinx-design; extra == "docs"
Requires-Dist: matplotlib; extra == "docs"
Dynamic: license-file
